devcli/__init__.py
devcli/context.py
devcli/devcli.py
devcli_gitlab/__init__.py
devcli_gitlab/add_file.py
devcli_gitlab/edit_file.py
devcli_gitlab/git_utils.py
devcli_gitlab/gitlab_client.py
devcli_gitlab/gitlab_group.py
devcli_gitlab/gitlab_utils.py
devcli_gitlab/run_script.py
devcli_gitlab/sync.py
devcli_gitlab/trigger_pipelines.py
devcli_npm_install/__init__.py
devcli_poetry_install/__init__.py
devcli-0.1.9.dist-info/entry_points.txt
devcli-0.1.9.dist-info/WHEEL
devcli-0.1.9.dist-info/METADATA
devcli-0.1.9.dist-info/RECORD
