Metadata-Version: 2.1
Name: devcli
Version: 0.1.9
Summary: 
Home-page: https://github.com/devnoo/dev-cli/
License: MIT
Author: Job de Noo
Author-email: jgdenoo@gmail.com
Requires-Python: >=3.8,<4.0
Classifier: License :: OSI Approved :: MIT License
Classifier: Programming Language :: Python :: 3
Classifier: Programming Language :: Python :: 3.8
Classifier: Programming Language :: Python :: 3.9
Requires-Dist: GitPython (>=3.1.11,<4.0.0)
Requires-Dist: PyYAML (>=5.3.1,<6.0.0)
Requires-Dist: cachetools (>=4.1.1,<5.0.0)
Requires-Dist: click (>=7.1.2,<8.0.0)
Requires-Dist: python-gitlab (>=2.5.0,<3.0.0)
Requires-Dist: python-graphql-client (>=0.4.0,<0.5.0)
Requires-Dist: ruamel.yaml (>=0.16.12,<0.17.0)
Requires-Dist: toml (>=0.10.2,<0.11.0)
Project-URL: Repository, https://github.com/devnoo/dev-cli/
